pylithiumsso3/__init__.py
pylithiumsso3/lithium_sso.py
pylithiumsso3-0.1.1.dist-info/LICENSE.TXT
pylithiumsso3-0.1.1.dist-info/METADATA
pylithiumsso3-0.1.1.dist-info/WHEEL
pylithiumsso3-0.1.1.dist-info/RECORD
